smart_time_py/__init__.py
smart_time_py/analysis.py
smart_time_py/calendar_integration.py
smart_time_py/converter.py
smart_time_py/formatters.py
smart_time_py/holidays.py
smart_time_py/periods.py
smart_time_py/timezone.py
smart_time_py-1.3.0.dist-info/licenses/LICENSE
tests/__init__.py
tests/test_analysis.py
tests/test_calendar_integration.py
tests/test_converter.py
tests/test_smart_time.py
smart_time_py-1.3.0.dist-info/METADATA
smart_time_py-1.3.0.dist-info/WHEEL
smart_time_py-1.3.0.dist-info/top_level.txt
smart_time_py-1.3.0.dist-info/RECORD
