Metadata-Version: 2.4
Name: smart-time-py
Version: 1.3.0
Summary: ⏳ Uma biblioteca avançada para manipulação de datas e tempos em Python
Home-page: https://github.com/robertolima-dev/smart-time-py
Author: Roberto Lima
Author-email: Roberto Lima <robertolima@example.com>
License: MIT
Project-URL: Homepage, https://github.com/robertolima/smart-time-py
Project-URL: Documentation, https://smart-time-py.readthedocs.io
Project-URL: Repository, https://github.com/robertolima/smart-time-py.git
Project-URL: Issues, https://github.com/robertolima/smart-time-py/issues
Keywords: date,time,datetime,timezone,holiday
Classifier: Development Status :: 4 - Beta
Classifier: Intended Audience :: Developers
Classifier: Programming Language :: Python :: 3
Classifier: Programming Language :: Python :: 3.8
Classifier: Programming Language :: Python :: 3.9
Classifier: Programming Language :: Python :: 3.10
Classifier: Programming Language :: Python :: 3.11
Classifier: Topic :: Software Development :: Libraries :: Python Modules
Requires-Python: >=3.6
License-File: LICENSE
Requires-Dist: pytz>=2023.3
Requires-Dist: python-dateutil>=2.8.2
Requires-Dist: babel>=2.12.1
Requires-Dist: google-api-python-client>=2.108.0
Requires-Dist: google-auth-httplib2>=0.1.1
Requires-Dist: google-auth-oauthlib>=1.1.0
Requires-Dist: icalendar>=5.0.7
Dynamic: author
Dynamic: home-page
Dynamic: license-file
Dynamic: requires-python
